burplabs/__init__.py
burplabs/cli.py
burplabs/labs/__init__.py
burplabs/labs/API/api_lab1.py
burplabs/labs/API/api_lab2.py
burplabs/labs/API/api_lab3.py
burplabs/labs/API/api_lab4.py
burplabs/labs/API/api_lab5.py
burplabs/labs/DOM-based-vuln/dom_based_lab1.py
burplabs/labs/DOM-based-vuln/dom_based_lab2.py
burplabs/labs/DOM-based-vuln/dom_based_lab3.py
burplabs/labs/DOM-based-vuln/dom_based_lab4.py
burplabs/labs/DOM-based-vuln/dom_based_lab5.py
burplabs/labs/NoSQL/no_sqli_lab1.py
burplabs/labs/NoSQL/no_sqli_lab2.py
burplabs/labs/NoSQL/no_sqli_lab3.py
burplabs/labs/NoSQL/no_sqli_lab4.py
burplabs/labs/OS-command-injection/os_injection_lab1.py
burplabs/labs/OS-command-injection/os_injection_lab2.py
burplabs/labs/OS-command-injection/os_injection_lab3.py
burplabs/labs/OS-command-injection/os_injection_lab4.py
burplabs/labs/OS-command-injection/os_injection_lab5.py
burplabs/labs/SSTI/ssti_lab1.py
burplabs/labs/SSTI/ssti_lab2.py
burplabs/labs/SSTI/ssti_lab3.py
burplabs/labs/SSTI/ssti_lab4.py
burplabs/labs/SSTI/ssti_lab5.py
burplabs/labs/XXE/xxe_lab1.py
burplabs/labs/XXE/xxe_lab2.py
burplabs/labs/XXE/xxe_lab3.py
burplabs/labs/XXE/xxe_lab4.py
burplabs/labs/XXE/xxe_lab5.py
burplabs/labs/XXE/xxe_lab6.py
burplabs/labs/XXE/xxe_lab7.py
burplabs/labs/XXE/xxe_lab8.py
burplabs/labs/access control vuln/access_control_lab1.py
burplabs/labs/access control vuln/access_control_lab10.py
burplabs/labs/access control vuln/access_control_lab11.py
burplabs/labs/access control vuln/access_control_lab12.py
burplabs/labs/access control vuln/access_control_lab13.py
burplabs/labs/access control vuln/access_control_lab2.py
burplabs/labs/access control vuln/access_control_lab3.py
burplabs/labs/access control vuln/access_control_lab4.py
burplabs/labs/access control vuln/access_control_lab5.py
burplabs/labs/access control vuln/access_control_lab6.py
burplabs/labs/access control vuln/access_control_lab7.py
burplabs/labs/access control vuln/access_control_lab8.py
burplabs-0.3.3.dist-info/METADATA
burplabs-0.3.3.dist-info/WHEEL
burplabs-0.3.3.dist-info/entry_points.txt
burplabs-0.3.3.dist-info/top_level.txt
burplabs-0.3.3.dist-info/RECORD
